{
  "empresa": {
    "nome": "LavandeRio - Soluções em Lavanderia Especializada",
    "cnpj": "11.222.333/0001-44",
    "fundacao": "2018",
    "sede": "Rio de Janeiro, RJ",
    "filiais": 8,
    "funcionarios": 145
  },
  "negocio": {
    "modelo": "B2B Lavanderia Especializada",
    "segmentos": ["Hotelaria", "Gastronomia", "Saúde", "Eventos", "Fitness"],
    "territorio": "Grande Rio de Janeiro",
    "capacidade_diaria": "2.5 toneladas de roupas",
    "tipos_servico": {
      "basic": "Lavagem padrão para academias e pequenos estabelecimentos",
      "standard": "Lavagem e passadoria para restaurantes e clínicas",
      "premium": "Lavagem, passadoria e tratamentos especiais para hotéis",
      "enterprise": "Soluções completas para hospitais e grandes redes"
    }
  },
  "desafios_financeiros": {
    "inadimplencia": "Taxa cresceu de 8.5% (out/23) para 16.7% (jan/24)",
    "sazonalidade": "Queda de 20% na receita entre dezembro e janeiro",
    "fluxo_caixa": "45 dias prazo médio vs 30 dias custo operacional",
    "clientes_problema": [
      "Pequenos restaurantes com alta rotatividade",
      "Academias com contratos de baixo valor",
      "Eventos sazonais com pagamentos irregulares"
    ]
  },
  "solucao_neofin": {
    "implementacao": "Setembro 2023",
    "modulos": ["Análise Preditiva", "Automação de Cobrança", "Gestão de Risco"],
    "resultados": {
      "reducao_inadimplencia": "Meta: -50% em 6 meses",
      "melhoria_fluxo": "Meta: reduzir prazo médio para 35 dias",
      "eficiencia_cobranca": "Meta: automatizar 80% das cobranças"
    }
  },
  "metricas_importantes": {
    "receita_mensal_media": 850000,
    "ticket_medio_geral": 29500,
    "margem_bruta_objetivo": 70,
    "cac_maximo": 1500,
    "ltv_minimo": 40000,
    "churn_maximo": 5
  },
  "segmentacao_clientes": {
    "enterprise": {
      "caracteristicas": "Hospitais e grandes hotéis",
      "ticket_medio": 70000,
      "inadimplencia": "Baixa (2%)",
      "prazo_pagamento": "30 dias"
    },
    "premium": {
      "caracteristicas": "Hotéis médios e spas",
      "ticket_medio": 35000,
      "inadimplencia": "Média (8%)",
      "prazo_pagamento": "30-45 dias"
    },
    "standard": {
      "caracteristicas": "Restaurantes e clínicas",
      "ticket_medio": 12000,
      "inadimplencia": "Alta (15%)",
      "prazo_pagamento": "45-60 dias"
    },
    "basic": {
      "caracteristicas": "Academias e pequenos estabelecimentos",
      "ticket_medio": 5500,
      "inadimplencia": "Muito alta (25%)",
      "prazo_pagamento": "60+ dias"
    }
  }
}